imTriangle.py
imTriangle-0.0.3.data/scripts/imTriangle
imTriangle-0.0.3.dist-info/METADATA
imTriangle-0.0.3.dist-info/WHEEL
imTriangle-0.0.3.dist-info/top_level.txt
imTriangle-0.0.3.dist-info/RECORD
