Metadata-Version: 2.1
Name: imTriangle
Version: 0.0.3
Summary: This snippet of code attempts to put triangle pixelation effect on images.
Home-page: https://github.com/Mamdasn/imTriangle
Author: mamdasn s
Author-email: <mamdassn@gmail.com>
License: UNKNOWN
Keywords: python,traingle effect,triangle pixelation effect
Platform: UNKNOWN
Classifier: Development Status :: 1 - Planning
Classifier: Intended Audience :: Science/Research
Classifier: License :: OSI Approved :: MIT License
Classifier: Programming Language :: Python :: 3.8
Classifier: Operating System :: OS Independent
Requires-Dist: numpy
Requires-Dist: numba
Requires-Dist: imPixelate
